nshconfig_extra/__init__.py
nshconfig_extra/file/__init__.py
nshconfig_extra/file/base.py
nshconfig_extra/file/cached_path_.py
nshconfig_extra/file/ssh.py
nshconfig_extra-0.10.0.dist-info/LICENSE
nshconfig_extra-0.10.0.dist-info/METADATA
nshconfig_extra-0.10.0.dist-info/WHEEL
nshconfig_extra-0.10.0.dist-info/RECORD
