Metadata-Version: 2.3
Name: nshconfig-extra
Version: 0.10.0
Summary: 
Author: Nima Shoghi
Author-email: nimashoghi@gmail.com
Requires-Python: >=3.9,<4.0
Classifier: Programming Language :: Python :: 3
Classifier: Programming Language :: Python :: 3.9
Classifier: Programming Language :: Python :: 3.10
Classifier: Programming Language :: Python :: 3.11
Classifier: Programming Language :: Python :: 3.12
Classifier: Programming Language :: Python :: 3.13
Provides-Extra: extra
Provides-Extra: ssh
Provides-Extra: test
Requires-Dist: cached-path
Requires-Dist: nshconfig
Requires-Dist: paramiko ; extra == "extra"
Requires-Dist: paramiko ; extra == "ssh"
Requires-Dist: pytest (>=7.0.0) ; extra == "test"
Requires-Dist: pytest-cov (>=4.0.0) ; extra == "test"
Requires-Dist: pytest-mock (>=3.10.0) ; extra == "test"
Project-URL: Homepage, https://github.com/nimashoghi/nshconfig-extra
